llama_search/__init__.py
llama_search/_constants.py
llama_search/_exceptions.py
llama_search/_logging.py
llama_search/_retry.py
llama_search/_utils.py
llama_search/client.py
llama_search/types/__init__.py
llama_search/types/account.py
llama_search/types/billing.py
llama_search/types/search.py
llama_search-0.3.4.dist-info/licenses/LICENSE
llama_search-0.3.4.dist-info/METADATA
llama_search-0.3.4.dist-info/WHEEL
llama_search-0.3.4.dist-info/top_level.txt
llama_search-0.3.4.dist-info/RECORD
