Metadata-Version: 2.4
Name: llama-search
Version: 0.3.4
Summary: Official Python SDK for Llama Search AI Platform
Author-email: Llama Search Team <support@llama-search.com>
License-Expression: MIT
Project-URL: Homepage, https://llama-search.com
Project-URL: Documentation, https://llama-search.com/docs
Project-URL: Repository, https://github.com/llama-search/llama-search
Requires-Python: >=3.10
License-File: LICENSE
Requires-Dist: httpx>=0.24.0
Requires-Dist: pydantic>=2.0.0
Requires-Dist: python-dotenv>=1.1.1
Requires-Dist: typing-extensions>=4.0.0
Provides-Extra: dev
Requires-Dist: pytest>=7.0.0; extra == "dev"
Requires-Dist: pytest-asyncio>=0.21.0; extra == "dev"
Requires-Dist: pytest-mock>=3.10.0; extra == "dev"
Requires-Dist: mypy>=1.7.0; extra == "dev"
Requires-Dist: ruff>=0.1.6; extra == "dev"
Requires-Dist: pre-commit>=3.5.0; extra == "dev"
Dynamic: license-file
